Metadata-Version: 2.1
Name: coi
Version: 0.0.7
Summary: See output/input status of all sub-folders
Home-page: https://github.com/nosarthur/coi
Author: Dong Zhou
Author-email: zhou.dong@gmail.com
License: MIT
Keywords: bash
Platform: linux
Platform: osx
Platform: win32
Classifier: Development Status :: 4 - Beta
Classifier: Intended Audience :: Developers
Classifier: License :: OSI Approved :: MIT License
Classifier: Operating System :: POSIX
Classifier: Operating System :: MacOS :: MacOS X
Classifier: Topic :: Software Development :: Version Control :: Git
Classifier: Topic :: Terminals
Classifier: Topic :: Utilities
Classifier: Programming Language :: Python :: 3.6
Classifier: Programming Language :: Python :: 3.7
Classifier: Programming Language :: Python :: 3.8
Classifier: Programming Language :: Python :: 3.9
Requires-Python: ~=3.6
